dcb/__init__.py
dcb/compoundloader.py
dcb/dcbenvironment.py
dcb/image.py
dcb/main.py
dcb/registry.py
dcb/setting.py
dcb/utils.py
dcb/snippets/ansible-playbook.j2
dcb/snippets/ansible-test-role.j2
dcb/snippets/dcb-bootstrap.j2
dcb/snippets/from.j2
dcb-0.1.3.dist-info/LICENSE
dcb-0.1.3.dist-info/METADATA
dcb-0.1.3.dist-info/WHEEL
dcb-0.1.3.dist-info/entry_points.txt
dcb-0.1.3.dist-info/top_level.txt
dcb-0.1.3.dist-info/RECORD
