Metadata-Version: 2.1
Name: dcb
Version: 0.1.3
Summary: CLI for building, tagging, and publishing Docker containers
Home-page: http://github.com/andrewrothstein/dcb
Author: Andrew Rothstein
Author-email: andrew.rothstein@gmail.com
License: MIT
Requires-Python: >=3.5
License-File: LICENSE
Requires-Dist: jinja2
Provides-Extra: test
Requires-Dist: nose2 ; extra == 'test'
